<stage>
  <width>768</width>
  <height>1024</height>
  <instrument>
    <uid>stage4_1</uid>
    <x>0</x>
    <y>0</y>
    <type>components.instruments.digital.DigitalA</type>
    <w>512</w>
    <h>256</h>
    <actualState>5</actualState>
  </instrument>
  <instrument>
    <uid>stage4_2</uid>
    <x>0</x>
    <y>256</y>
    <type>components.instruments.digital.DigitalA</type>
    <w>512</w>
    <h>256</h>
    <actualState>4</actualState>
  </instrument>
  <instrument>
    <uid>stage4_3</uid>
    <x>0</x>
    <y>512</y>
    <type>components.instruments.digital.DigitalA</type>
    <w>512</w>
    <h>256</h>
    <actualState>9</actualState>
  </instrument>
  <instrument>
    <uid>stage4_4</uid>
    <x>512</x>
    <y>0</y>
    <type>components.instruments.digital.DigitalE</type>
    <w>256</w>
    <h>128</h>
    <actualState>5</actualState>
  </instrument>
  <instrument>
    <uid>stage4_5</uid>
    <x>512</x>
    <y>128</y>
    <type>components.instruments.digital.DigitalE</type>
    <w>256</w>
    <h>128</h>
    <actualState>4</actualState>
  </instrument>
  <instrument>
    <uid>stage4_6</uid>
    <x>512</x>
    <y>256</y>
    <type>components.instruments.digital.DigitalE</type>
    <w>256</w>
    <h>128</h>
    <actualState>5</actualState>
  </instrument>
  <instrument>
    <uid>stage4_7</uid>
    <x>512</x>
    <y>384</y>
    <type>components.instruments.digital.DigitalE</type>
    <w>256</w>
    <h>128</h>
    <actualState>4</actualState>
  </instrument>
  <instrument>
    <uid>stage4_8</uid>
    <x>512</x>
    <y>512</y>
    <type>components.instruments.digital.DigitalE</type>
    <w>256</w>
    <h>128</h>
    <actualState>5</actualState>
  </instrument>
  <instrument>
    <uid>stage4_9</uid>
    <x>512</x>
    <y>640</y>
    <type>components.instruments.digital.DigitalE</type>
    <w>256</w>
    <h>128</h>
    <actualState>4</actualState>
  </instrument>
  <instrument>
    <uid>stage4_10</uid>
    <x>0</x>
    <y>768</y>
    <type>components.instruments.digital.DigitalA</type>
    <w>512</w>
    <h>256</h>
    <actualState>9</actualState>
  </instrument>
  <instrument>
    <uid>stage4_11</uid>
    <x>512</x>
    <y>768</y>
    <type>components.instruments.digital.DigitalE</type>
    <w>256</w>
    <h>128</h>
    <actualState>5</actualState>
  </instrument>
  <instrument>
    <uid>stage4_12</uid>
    <x>512</x>
    <y>896</y>
    <type>components.instruments.digital.DigitalE</type>
    <w>256</w>
    <h>128</h>
    <actualState>4</actualState>
  </instrument>
</stage>